django_static_adminlte/.DS_Store
django_static_adminlte/__init__.py
django_static_adminlte/admin.py
django_static_adminlte/apps.py
django_static_adminlte/models.py
django_static_adminlte/tests.py
django_static_adminlte/views.py
django_static_adminlte/migrations/__init__.py
django_static_adminlte/static/.DS_Store
django_static_adminlte/static/adminlte/.DS_Store
django_static_adminlte/static/adminlte/css/adminlte.css
django_static_adminlte/static/adminlte/css/adminlte.css.map
django_static_adminlte/static/adminlte/css/adminlte.min.css
django_static_adminlte/static/adminlte/css/adminlte.min.css.map
django_static_adminlte/static/adminlte/css/alt/adminlte.components.css
django_static_adminlte/static/adminlte/css/alt/adminlte.components.css.map
django_static_adminlte/static/adminlte/css/alt/adminlte.components.min.css
django_static_adminlte/static/adminlte/css/alt/adminlte.components.min.css.map
django_static_adminlte/static/adminlte/css/alt/adminlte.core.css
django_static_adminlte/static/adminlte/css/alt/adminlte.core.css.map
django_static_adminlte/static/adminlte/css/alt/adminlte.core.min.css
django_static_adminlte/static/adminlte/css/alt/adminlte.core.min.css.map
django_static_adminlte/static/adminlte/css/alt/adminlte.extra-components.css
django_static_adminlte/static/adminlte/css/alt/adminlte.extra-components.css.map
django_static_adminlte/static/adminlte/css/alt/adminlte.extra-components.min.css
django_static_adminlte/static/adminlte/css/alt/adminlte.extra-components.min.css.map
django_static_adminlte/static/adminlte/css/alt/adminlte.light.css
django_static_adminlte/static/adminlte/css/alt/adminlte.light.css.map
django_static_adminlte/static/adminlte/css/alt/adminlte.light.min.css
django_static_adminlte/static/adminlte/css/alt/adminlte.light.min.css.map
django_static_adminlte/static/adminlte/css/alt/adminlte.pages.css
django_static_adminlte/static/adminlte/css/alt/adminlte.pages.css.map
django_static_adminlte/static/adminlte/css/alt/adminlte.pages.min.css
django_static_adminlte-3.2.0.3.dist-info/licenses/LICENSE
django_static_adminlte-3.2.0.3.dist-info/METADATA
django_static_adminlte-3.2.0.3.dist-info/WHEEL
django_static_adminlte-3.2.0.3.dist-info/top_level.txt
django_static_adminlte-3.2.0.3.dist-info/RECORD
