Metadata-Version: 2.4
Name: django-static-adminlte
Version: 3.2.0.3
Summary: Django application contain adminlte static files.
Author: rRR0VrFP
Maintainer: rRR0VrFP
License: MIT
Keywords: django-static-adminlte
Classifier: Development Status :: 5 - Production/Stable
Classifier: Intended Audience :: Developers
Classifier: Topic :: Software Development :: Libraries :: Python Modules
Classifier: License :: OSI Approved :: MIT License
Classifier: Programming Language :: Python :: 3
Classifier: Programming Language :: Python :: 3 :: Only
License-File: LICENSE
Requires-Dist: django
Requires-Dist: django-static-fontawesome
Requires-Dist: django-static-ionicons
Requires-Dist: django-static-jquery3
Requires-Dist: django-static-bootstrap
Dynamic: author
Dynamic: classifier
Dynamic: description
Dynamic: description-content-type
Dynamic: keywords
Dynamic: license
Dynamic: license-file
Dynamic: maintainer
Dynamic: requires-dist
Dynamic: summary
